Metadata-Version: 1.1
Name: Sesam-JackTop
Version: 0.0.1
Summary: Sesam Software Jacket and Topside Helper Tools
Home-page: UNKNOWN
Author: abinpulivelil
Author-email: abinpulivelil@gmail.com
License: MIT
Keywords: Sesam GeniE
Platform: UNKNOWN
Classifier: Development Status :: 5 - Production/Stable
Classifier: Intended Audience :: Education
Classifier: Operating System :: Microsoft :: Windows :: Windows 10
Classifier: License :: OSI Approved :: MIT License
Classifier: Programming Language :: Python :: 3
